pbfetch/__init__.py
pbfetch/__main__.py
pbfetch/config.py
pbfetch/constants.py
pbfetch/fetch.py
pbfetch/handle_error.py
pbfetch/horizontal_formatter.py
pbfetch/stats.py
pbfetch/parse/__init__.py
pbfetch/parse/battery.py
pbfetch/parse/bios_type.py
pbfetch/parse/computer_name.py
pbfetch/parse/cpu.py
pbfetch/parse/cpu_temp.py
pbfetch/parse/cpu_usage.py
pbfetch/parse/de.py
pbfetch/parse/disk.py
pbfetch/parse/font.py
pbfetch/parse/fs.py
pbfetch/parse/gpu.py
pbfetch/parse/hostname.py
pbfetch/parse/kernel.py
pbfetch/parse/login.py
pbfetch/parse/memory.py
pbfetch/parse/motherboard.py
pbfetch/parse/os.py
pbfetch/parse/packages.py
pbfetch/parse/resolution.py
pbfetch/parse/shell.py
pbfetch/parse/temp.py
pbfetch/parse/term_font.py
pbfetch/parse/theme.py
pbfetch/parse/uptime.py
pbfetch/parse/weather.py
pbfetch/parse/wm.py
pbfetch-0.3.6.dist-info/METADATA
pbfetch-0.3.6.dist-info/WHEEL
pbfetch-0.3.6.dist-info/entry_points.txt
pbfetch-0.3.6.dist-info/licenses/LICENSE
pbfetch-0.3.6.dist-info/RECORD
