Metadata-Version: 2.3
Name: pbfetch
Version: 0.3.6
Summary: An unbelievably customizable hardware/software fetch.
Project-URL: Homepage, https://github.com/pennybelle/pbfetch/
Project-URL: Repository, https://github.com/pennybelle/pbfetch.git
Project-URL: Issues, https://github.com/pennybelle/pbfetch/issues
Author-email: pennybelle <contact@pennybelle.dev>
Classifier: License :: OSI Approved :: Apache Software License
Requires-Python: >=3.8
Requires-Dist: psutil
